setup.py
accenter/__init__.py
accenter/accenter.py
accenter.egg-info/PKG-INFO
accenter.egg-info/SOURCES.txt
accenter.egg-info/dependency_links.txt
accenter.egg-info/not-zip-safe
accenter.egg-info/top_level.txt
bin/accenter