Metadata-Version: 1.0
Name: accenter
Version: 0.1
Summary: Put random accents on words. Test package.
Home-page: http://github.com/steveandroulakis/accenter
Author: Steve Androulakis
Author-email: steve.androulakis@gmail.com
License: MIT
Platform: UNKNOWN
